fastkmeans/__init__.py
fastkmeans/kmeans.py
fastkmeans/triton_kernels.py
fastkmeans-0.5.0.dist-info/licenses/LICENSE
fastkmeans-0.5.0.dist-info/METADATA
fastkmeans-0.5.0.dist-info/WHEEL
fastkmeans-0.5.0.dist-info/top_level.txt
fastkmeans-0.5.0.dist-info/RECORD
