Metadata-Version: 2.4
Name: fastkmeans
Version: 0.5.0
Summary: Add your description here
Author-email: Ben Clavié <bc@answer.ai>, Benjamin Warner <bw@answer.ai>
Maintainer-email: Ben Clavié <bc@answer.ai>, Benjamin Warner <bw@answer.ai>
License: Apache-2.0
Requires-Python: >=3.8
License-File: LICENSE
Requires-Dist: torch
Requires-Dist: numpy
Dynamic: license-file
